{
    ttls: {"en":"Judaism (forgotten)", "he":"יהדות (נשכחים)"},
    defLocale: "he",
    cal: "heb*",
    color: {name: "blue"},
    evts: [
        {ttls: {"he":"שמחת כהן", "en":"Simḥath Kohen"}, type: "D", st: {mon: 1, d: 11}, notes: {"he":"עיונים של רבן שטיינזלץ על יומא ע׳ ע״א"}},
        {ttls: {"he":"יום טוב שני של יום כיפור", "en":"Yom Kippur (yom ṭov sheni)"}, type: "D", st: {mon: 1, d: 11}, "excludeRegionCodes": ["IL", "PS"], notes: {"he":"ראש השנה כ״א ע״א"}},
        {ttls: {"he":"יום טוב שני של בני פרעוש בן יהודה", "en":"Second Festival of Bene Par‘osh ben Yehudhah"}, type: "D", st: {mon: 4, d: 1}, notes: {"he":"תענית כ״ו ע״א, תענית כ״ח ע״א"}},
        {ttls: {"he":"יום הר גריזים (לפי תלמוד בבלי)", "en":"Mount Gerizim Day (according to Talmudh Bavli)"}, type: "D", st: {mon: 4, d: 25}, notes: {"he":"יומא ס״ט ע״א"}},
        {ttls: {"he":"יום טוריינוס", "en":"Ṭuryanus Day"}, type: "D", st: {mon: 7, d: 12}, notes: {"he":"תענית י״ח ע״ב, מגילת תענית"}},
        {ttls: {"he":"יום ניקנור", "en":"Niqanor Day"}, type: "D", st: {mon: 7, d: 13}, notes: {"he":"תענית י״ח ע״ב, מגילת תענית"}},
        {ttls: {"he":"יומא דביה אתת בשורתא טבתא ליהודאי דלא יעידון מן אורייתא", "en":"Day in Which Came Good News to the Jews That They Should Not Deviate from the Torah"}, type: "D", st: {mon: 7, d: 28}, notes: {"he":"ראש השנה י״ט ע״א, תענית י״ח ע״א, מגילת תענית"}},
        {ttls: {"he":"יום טוב של בני ארח בן יהודה", "en":"Festival of Bene ’Araḥ ben Yehudhah"}, type: "D", st: {mon: 8, d: 1}, notes: {"he":"תענית כ״ו ע״א"}},
        {ttls: {"he":"יומיא דבהו איתוקם תמידא", "en":"Tamidh Establishment Days"}, type: "nD", st: {mon: 8, d: 1}, end: {mon: 8, d: 8}, notes: {"he":"תענית י״ז ע״ב־י״ח ע״א, מנחות ס״ה ע״א"}, emoji: "🐑"},
        {ttls: {"he":"יומיא דבהו איתותב חגא דשבועיא", "en":"Shavu‘oth Settlement Days"}, type: "nD", st: {mon: 8, d: 8}, end: {mon: 8, d: 21}, notes: {"he":"תענית י״ז ע״ב, תענית י״ח ע״א, מנחות ס״ה ע״א־ע״ב"}},
        {ttls: {"he":"ראש השנה לעומר", "en":"New Year for the ‘Omer"}, type: "D", st: {mon: 8, d: 16}, notes: {"he":"ראש השנה ז׳ ע״ב"}},
        {ttls: {"he":"ראש השנה לשתי הלחם", "en":"New Year for the Two Loaves"}, type: "D", st: {mon: 10, d: 6}, notes: {"he":"ראש השנה ז׳ ע״ב, מגילה ל״א ע״ב"}},
        {ttls: {"he":"יום טוב של בני דוד בן יהודה", "en":"Festival of Bene Dawidh ben Yehudhah"}, type: "D", st: {mon: 10, d: 20}, notes: {"he":"תענית כ״ו ע״א"}},
        {ttls: {"he":"יום טוב ראשון של בני פרעוש בן יהודה", "en":"First Festival of Bene Par‘osh ben Yehudhah"}, type: "D", st: {mon: 12, d: 5}, notes: {"he":"תענית כ״ו ע״א"}},
        {ttls: {"he":"יום טוב של יונדב בן רכב", "en":"Festival of Yonadhav ben Rekhav"}, type: "D", st: {mon: 12, d: 7}, notes: {"he":"תענית כ״ו ע״א"}},
        {ttls: {"he":"יום טוב של בני סנאב (או:  סנאה) בן בנימין", "en":"Festival of Sena’av (or:  Sena’ah) ben Binyamin"}, type: "D", st: {mon: 12, d: 10}, notes: {"he":"תענית י״ב ע״א, תענית כ״ו ע״א"}},
        {ttls: {"he":"יום טוב של בני זתוא בן יהודה ועמהם כהנים ולוים וכל מי שטעה בשבטו ובני גונבי עלי ובני קוצעי קציעות", "en":"Festival of Bene Zattu’ ben Yehudhah and with Them Kohanim and Lewiyyim and All Who Wandered with His Tribe and Bene Goneve ‘Eli and Bene Qoṣe‘e Qeṣi‘oth"}, type: "D", st: {mon: 12, d: 15}, notes: {"he":"תענית כ״ו ע״א"}},
        {ttls: {"he":"יום טוב של בני פחת מואב בן יהודה", "en":"Festival of Bene Paḥath Mo’av ben Yehudhah"}, type: "D", st: {mon: 12, d: 20}, notes: {"he":"תענית כ״ו ע״א"}},
        {ttls: {"he":"יום טוב של בני עדין בן יהודה", "en":"Festival of Bene ‘Adhin ben Yehudhah"}, type: "D", st: {mon: 13, d: 20}, notes: {"he":"תענית כ״ו ע״א, תענית כ״ח ע״א"}},
        
        {ttls: {"he":"חנוכת שור ירושלים", "en":"Wall of Yerushalayim Dedication Day"}, type: "D", st: {mon: 9, d: 7}, notes: {"he":"מגילת תענית"}},
        {ttls: {"he":"יומא דביה נפקו בני חקרא מירושלם", "en":"Day in Which Bene Ḥaqra’ Went Out of Yerushalayim"}, type: "D", st: {mon: 9, d: 23}, notes: {"he":"מגילת תענית"}},
        {ttls: {"he":"יומא דביה איתנטילו כלילאי מיהודה ומירושלם", "en":"Day in Which the Coronation Tax Was Remitted from Yehudhah and Yerushalayim"}, type: "D", st: {mon: 9, d: 27}, notes: {"he":"מגילת תענית"}},
        {ttls: {"he":"אחידת מגדל צור", "en":"Conquest of the Tower of Ṣur"}, type: "D", st: {mon: 10, d: 17}, notes: {"he":"מגילת תענית"}},
        {ttls: {"he":"ימים שבהם גלו אנשי בית שאן ואנשי בקעתא", "en":"Days in Which Were Exiles the People of Beth She’an and Baq‘atha’"}, type: "nD", st: {mon: 10, d: 15}, end: {mon: 10, d: 16}, notes: {"he":"מגילת תענית"}},
        {ttls: {"he":"יומא דביה איתנטילו דימסנאי מיהודה וירושלים", "en":"Day in Which Public Revenue Farmers Were Removed from Yehudhah and Yerushalayim"}, type: "D", st: {mon: 10, d: 25}, notes: {"he":"מגילת תענית"}},
        {ttls: {"he":"יומא דביה עדא ספר גזרתא", "en":"Book of Enactments Nullification Day"}, type: "D", st: {mon: 11, d: 14}, notes: {"he":"מגילת תענית"}},
        {ttls: {"he":"יומא דביה תבנא לדיננא", "en":"Reestablishment of Jewish Law Day"}, type: "D", st: {mon: 12, d: 24}, notes: {"he":"מגילת תענית"}},
        {ttls: {"he":"חנוכת שור ירושלם", "en":"Wall of Yerushalayim Dedication Day"}, type: "D", st: {mon: 13, d: 7}, notes: {"he":"מגילת תענית"}},
        {ttls: {"he":"יומא דביה נפקו רומאי מן ירושלם", "en":"Romans Leave Yerushalayim  Day"}, type: "D", st: {mon: 13, d: 17}, notes: {"he":"מגילת תענית"}},
        {ttls: {"he":"יומא דביה תבו לקטלא משמדיא", "en":"Death Penalty Restoration Day"}, type: "D", st: {mon: 13, d: 22}, notes: {"he":"מגילת תענית"}},
        {ttls: {"he":"בטילת אדכרתא מן שטריא", "en":"Cancelation of Use of the Tetragrammaton in Documents Day"}, type: "D", st: {mon: 1, d: 3}, notes: {"he":"מגילת תענית"}},
        {ttls: {"he":"יומא דביה אסתתר סוריגא מן עזרתא", "en":"Tearing Down of the Soregh Day"}, type: "D", st: {mon: 2, d: 23}, notes: {"he":"מגילת תענית"}},
        {ttls: {"he":"יומא דביה אחידת שומרון שורא", "en":"Capture of Samaria Day"}, type: "D", st: {mon: 2, d: 25}, notes: {"he":"מגילת תענית"}},
        {ttls: {"he":"יומא דביה תבת סולתא למיסק על מדבחא", "en":"Resumption of Offering Fine Flour on the Altar Day"}, type: "D", st: {mon: 2, d: 27}, notes: {"he":"מגילת תענית"}},
        {ttls: {"he":"יומא דביה אתנטילו סימותא מן דרתא", "en":"Removal of Idols from the Temple Courtyard Day"}, type: "D", st: {mon: 3, d: 3}},
        {ttls: {"he":"יום־שנה של הורדוס", "en":"Yohrtsayt of Herod"}, type: "D", st: {mon: 3, d: 7}, emoji: "🥳"},
        {ttls: {"he":"יום הר גריזים (לפי מגילת תענית)", "en":"Mount Gerizim Day (according to Meghillath Ta‘anith)"}, type: "D", st: {mon: 3, d: 21}, notes: {"he":"מגילת תענית"}},
        {ttls: {"he":"יום שמעון בן שטח (יתיבא כנישתא על דינא)", "en":"Shim‘on ben Sheṭaḥ Day (Sanhedhrin Sitting in Judgement Day)"}, type: "D", st: {mon: 4, d: 28}, notes: {"he":"מגילת תענית"}},
        {ttls: {"he":"יום־שנה של ינאי המלך", "en":"Yohrtsayt of King Yanna’y"}, type: "D", st: {mon: 5, d: 2}, emoji: "🥳", notes: {"he":"מגילת תענית"}},
        {ttls: {"he":"יום ביטול גזרת האויב להעמיד צלם בהיכל (יומא דביה בטילת עבידתא דאמר סנאה להיתאה להיכלא)", "en":"Cancelation of the Enemy’s Decree to Bring an Idol into the Temple Day"}, type: "D", st: {mon: 5, d: 22}, notes: {"he":"מגילת תענית"}},
        {ttls: {"he":"יום יציאת אנטיוכוס המלך מירושלים (יומא דביה אינטיל אנטיוכוס מלכא מן ירושלם)", "en":"King Antiochus Leaves Yerushalayim Day"}, type: "D", st: {mon: 5, d: 28}},
        {ttls: {"he":"יום תרועת מיטרא", "en":"Blowing the Shofar for Rain Day"}, type: "nD", st: {mon: 7, d: 8}, end: {mon: 7, d:9}, notes: {"he":"מגילת תענית"}, emoji: "🌧"},
        {ttls: {"he":  "יומא דביה שריו למבני שורא דירושלם", "en":"City Wall of Yerushalayim Building Day"}, type: "D", st: {mon: 7, d: 16}},
        {ttls: {"he":  "יומא דביה קמו עממיא על פלטת ספריא במדינת כלקיס בבית זבדי והוה פורקן", "en":"Day of Salvation of the Refugees of Safriyya’ in Kalqis and Beth Zavdi from the Gentiles"}, type: "D", st: {mon: 7, d: 17}},
        {ttls: {"he":  "יומא דביה צמון עמא על מטרא ונחת להון", "en":"Fasting for Rain Day"}, type: "D", st: {mon: 7, d: 20}, emoji: "🌧"},

        {ttls: {"he":  "פורים מועד קטן/אבן אלחסן", "en":"Purim of Shiraz/Purim of Mo‘edh Qaṭan)"}, type: "D", st: {mon: 2, d: 2}, fst: {era: 0, y: 4960}, urls: {"en":"https://www.jewishencyclopedia.com/articles/12450-purims-special#anchor23"}},
        {ttls: {"he":  "פורים נרבונה", "en":"Purim of Narbonne)"}, type: "D", st: {mon: 7, d: 21}, fst: {era: 0, y: 4996}, urls: {"en":"https://www.jewishencyclopedia.com/articles/12450-purims-special#anchor17"}},
        {ttls: {"he":  "פורים קסטיליה", "en":"Purim of Castile)"}, type: "D", st: {mon: 7, d: 21}, fst: {era: 0, y: 5099}},
        {ttls: {"he":  "פורים סרגוסה", "en":"Purim of Saragossa)"}, type: "D", st: {mon: 5, d: 18}, urls: {"en":"https://www.jewishencyclopedia.com/articles/12450-purims-special#anchor21"}},
        {ttls: {"he":  "פורים קנדיה", "en":"Purim of Candia)"}, type: "D", st: {mon: 11, d: 18}, fst: {era: 0, y: 5298}, urls: {"en":"https://www.jewishencyclopedia.com/articles/12450-purims-special#anchor6"}},
        {ttls: {"he":  "פורים אנאצרא/פורים הנוצרים", "en":"Purim ’Anaṣara’/Purim of the Christians"}, type: "D", st: {mon: 2, d: 4}, fst: {era: 0, y: 5301}},
        {ttls: {"he":  "פורים שני דרומא", "en":"Second Purim of Rome"}, type: "D", st: {mon: 9, d: 3}, fst: {era: 0, y: 5315}},
        {ttls: {"he":  "פורים של הנוצרים/פורים דה לוס כריסטיאנוס/פורים דה לאס בומבאס", "en":"Purim de los Christianos/Purim de las Bombas"}, type: "D", st: {mon: 13, d: 1}, fst: {era: 0, y: 5338}, urls: {"en":"https://www.jewishencyclopedia.com/articles/12450-purims-special#anchor9"}},
        {ttls: {"he":  "פורים וינץ", "en":"Purim Winz/Purim Frankfurt)"}, type: "D", st: {mon: 7, d: 20}, fst: {era: 0, y: 5376}, urls: {"en":"https://www.jewishencyclopedia.com/articles/12450-purims-special#anchor28"}},
        {ttls: {"he":  "פורים די בודה", "en":"Purim of Buda/Purim di Buda"}, type: "D", st: {mon: 13, d: 10}, fst: {era: 0, y: 5444}, urls: {"en":"https://www.jewishencyclopedia.com/articles/3795-buda-purim-of"}},
        {ttls: {"he":  "פורים ל״ג בעומר", "en":"Purim Lagh ba‘Omer"}, type: "D", st: {mon: 9, d: 18}, fst: {era: 0, y: 5450}},
        {ttls: {"he":  "פורים אנקונה", "en":"Purim of Ancona"}, type: "D", st: {mon: 4, d: 21}, fst: {era: 0, y: 5451}, urls: {"en":"https://www.jewishencyclopedia.com/articles/12450-purims-special#anchor2"}},
        {ttls: {"he":  "פורים של לונדענבורג", "en":"Purim of Lundenburg"}, type: "D", st: {mon: 4, d: 11}, fst: {era: 0, y: 5458}},
        {ttls: {"he":  "פורים צנעא", "en":"Purim Ṣin‘a’"}, type: "D", st: {mon: 7, d: 18}, fst: {era: 0, y: 5482}},
        {ttls: {"he":  "פורים פוזנה", "en":"Purim of Poznań"}, type: "D", st: {mon: 2, d: 3}, fst: {era: 0, y: 5464}},
        {ttls: {"he":  "פורים אשריף", "en":"Purim Sherif"}, type: "D", st: {mon: 4, d: 24}, fst: {era: 0, y: 5465}, urls: {"en":"https://www.jewishencyclopedia.com/articles/12450-purims-special#anchor22"}},
        {ttls: {"he":  "פורים בגדאד", "en":"Purim of Baghdad"}, type: "D", st: {mon: 12, d: 11}, fst: {era: 0, y: 5493}},
        {ttls: {"he":  "פורים ליבורנו", "en":"Purim of Livorno"}, type: "D", st: {mon: 5, d: 22}, fst: {era: 0, y: 5502}},
        {ttls: {"he":  "פורים טבריה א׳", "en":"Purim of Tiberias I"}, type: "D", st: {mon: 13, d: 4}, fst: {era: 0, y: 5503}, urls: {"en":"https://www.jewishencyclopedia.com/articles/12450-purims-special#anchor25"}},
        {ttls: {"he":  "פורים טבריה ב׳", "en":"Purim of Tiberias II"}, type: "D", st: {mon: 13, d: 7}, fst: {era: 0, y: 5503}, urls: {"en":"https://www.jewishencyclopedia.com/articles/12450-purims-special#anchor25"}},
        {ttls: {"he":  "פורים מסטיסלב", "en":"Purim of Mstsislaw"}, type: "D", st: {mon: 5, d: 4}, fst: {era: 0, y: 5504}},
        {ttls: {"he":  "פורים אוראן", "en":"Purim of ’Ura’n"}, type: "D", st: {mon: 12, d: 6}, fst: {era: 0, y: 5590}},
        {ttls: {"he":  "פורים מרוקו", "en":"Purim of Morocco"}, type: "D", st: {mon: 8, d: 14}, fst: {era: 0, y: 5531}},
        {ttls: {"he":  "פורים אלג׳יר", "en":"Purim of Tammuz at Algiers"}, type: "D", st: {mon: 11, d: 11}, fst: {era: 0, y: 5535}, urls: {"en":"https://www.jewishencyclopedia.com/articles/12450-purims-special#anchor24"}},
        {ttls: {"he":  "פורים אוסטראה", "en":"Purim of ’Usaṭara’ah"}, type: "D", st: {mon: 11, d: 7}, fst: {era: 0, y: 5542}},
        {ttls: {"he":  "פורים פירנצה", "en":"Purim of Florence"}, type: "D", st: {mon: 3, d: 27}, fst: {era: 0, y: 5550}, urls: {"en":"https://www.jewishencyclopedia.com/articles/12450-purims-special#anchor11"}},
        {ttls: {"he":  "פורים של רומא", "en":"Purim of Rome"}, type: "D", st: {mon: 5, d: 2}, fst: {era: 0, y: 5553}},
        {ttls: {"he":  "פורים וילנה", "en":"Purim of Vilnius"}, type: "D", st: {mon: 12, d: 15}, fst: {era: 0, y: 5554}},
        {ttls: {"he":  "פורים ברגל", "en":"Purim Borghel"}, type: "D", st: {mon: 4, d: 29}, fst: {era: 0, y: 5555}, urls: {"en":"https://www.jewishencyclopedia.com/articles/12450-purims-special#anchor4"}},
        {ttls: {"he":  "פורים שרפה", "en":"Purim of Burning"}, type: "D", st: {mon: 3, d: 11}, fst: {era: 0, y: 5555}},
        {ttls: {"he":  "פורים אורבינו", "en":"Purim of Urbino"}, type: "D", st: {mon: 10, d: 11}, fst: {era: 0, y: 5559}},
        {ttls: {"he":  "פורים סיניגאליה", "en":"Purim of Sinighalyah"}, type: "D", st: {mon: 10, d: 15}, fst: {era: 0, y: 5559}},
        {ttls: {"he":  "פורים סיינה", "en":"Purim of Siena"}, type: "D", st: {mon: 10, d: 15}, fst: {era: 0, y: 5559}},
        {ttls: {"he":"פורים וידין", "en":"Purim of Widdin"}, type: "nD", st: {mon: 2, d: 9}, fst: {era: 0, y: 5566}, end: {mon: 2, d: 10}, urls: {"en":"https://www.jewishencyclopedia.com/articles/12450-purims-special#anchor27"}},
        {ttls: {"he":  "פורים בוסניה", "en":"Purim of Bosnia"}, type: "D", st: {mon: 2, d: 4}, fst: {era: 0, y: 5580}},
        {ttls: {"he":  "פורים בלגרד", "en":"Purim of Belgrade"}, type: "D", st: {mon: 10, d: 19}, fst: {era: 0, y: 5582}},
        {ttls: {"he":  "פורים די לכור (המקלעים)", "en":"Purim of the Machine Guns"}, type: "D", st: {mon: 3, d: 22}, fst: {era: 0, y: 5591}},
        {ttls: {"he":  "פורים רודוס", "en":"Purim of Rhodes"}, type: "D", st: {mon: 7, d: 14}, urls: {"en":"https://www.jewishencyclopedia.com/articles/12450-purims-special#anchor20"}},
        {ttls: {"he":  "פורים איברהים פחה", "en":"Purim of ’Ibrahim Faḥah"}, type: "D", st: {mon: 9, d: 19}, fst: {era: 0, y: 5594}},
        {ttls: {"he":  "פורים שלג", "en":"Purim of Snow"}, type: "D", st: {mon: 4, d: 24}, fst: {era: 0, y: 5651}},
        {ttls: {"he":  "פורים היטלר", "en":"Purim of Hitler"}, type: "D", st: {mon: 3, d: 2}, fst: {era: 0, y: 5703}},
        {ttls: {"he":  "פורים של יהודי רומניה/פורים דרומניה", "en":"Purim of the Jews of Romania"}, type: "D", st: {mon: 13, d: 4}, fst: {era: 0, y: 5704}},
        {ttls: {"he":  "פורים של משפחת שמואל הנגיד", "en":"Purim of the Family of Shemu’el hanNaghidh"}, type: "D", st: {mon: 13, d: 1}, fst: {era: 0, y: 4799}},
        {ttls: {"he":  "פורים של משפחת ר׳ חנוך בן משה אלטשול", "en":"Purim Fürhang/Curtain Purim"}, type: "D", st: {mon: 4, d: 22}, fst: {era: 0, y: 5383}, urls: {"en":"https://www.jewishencyclopedia.com/articles/12450-purims-special#anchor13"}},
        {ttls: {"he":  "פורים של משפחת מיוחס", "en":"Purim of the Meyuḥas Family"}, type: "D", st: {mon: 7, d: 16}, fst: {era: 0, y: 5484}},
        {ttls: {"he":  "פורים של יום טוב ליפמן הלר", "en":"Purim of Yom Ṭov Lipmann Heller"}, type: "D", st: {mon: 7, d: 1}, urls: {"en":"https://www.jewishencyclopedia.com/articles/12450-purims-special#anchor29"}},
        {ttls: {"he":  "תענית של יום טוב ליפמן הלר", "en":"Fast of Yom Ṭov Lipmann Heller"}, type: "D", st: {mon: 11, d: 5}, fst: {era: 0, y: 5390}, urls: {"en":"https://www.jewishencyclopedia.com/articles/12450-purims-special#anchor29"}},
        {ttls: {"he":  "פולווערפורים", "en":"Purim of Abraham Danzig/Pulverpurim"}, type: "D", st: {mon: 3, d: 16}, fst: {era: 0, y: 5404}, urls: {"en":"https://www.jewishencyclopedia.com/articles/12450-purims-special#anchor1"}},
        {ttls: {"he":  "פורים אנגורה", "en":"Purim of Angora"}, type: "D", st: {mon: 9, d: 4}, urls: {"en":"https://www.jewishencyclopedia.com/articles/12450-purims-special#anchor3"}},
        {ttls: {"he":  "פורים קהיר", "en":"Purim of Cairo"}, type: "D", st: {mon: 7, d: 28}, urls: {"en":"https://www.jewishencyclopedia.com/articles/12450-purims-special#anchor6"}},
        {ttls: {"he":  "פורים אדום", "en":"Purim Edom/Purim al-Naāra"}, type: "D", st: {mon: 2, d: 4}, urls: {"en":"https://www.jewishencyclopedia.com/articles/12450-purims-special#anchor10"}},
        {ttls: {"he":  "פורים פדובה", "en":"Purim of Padua/Purim di Fuoco"}, type: "D", st: {mon: 10, d: 12}, urls: {"en":"https://www.jewishencyclopedia.com/articles/12450-purims-special#anchor18"}},
        {ttls: {"he":  "פורים הגנבים", "en":"Purim of Gumeldjina/Purim de los Ladrones"}, type: "D", st: {mon: 13, d: 22}, urls: {"en":"https://www.jewishencyclopedia.com/articles/12450-purims-special#anchor14"}},
        {ttls: {"he":  "פורים שלי/פורים של ר׳ יונתן בן יעקב מפולדה", "en":"Purim of Jonathan b. Jacob of Fulda"}, type: "D", st: {mon: 11, d: 17}, urls: {"en":"https://www.jewishencyclopedia.com/articles/12450-purims-special#anchor15"}},
        {ttls: {"he":  "פורים לפנטו", "en":"Purim of Lepanto"}, type: "D", st: {mon: 4, d: 11}, urls: {"en":"https://www.jewishencyclopedia.com/articles/12450-purims-special#anchor16"}},
        {ttls: {"he":  "פורים ריבת שזיפים", "en":"Purim Povidl/Plum-Jam Purim"}, type: "D", st: {mon: 7, d: 10}, urls: {"en":"https://www.jewishencyclopedia.com/articles/12450-purims-special#anchor19"}},
        {ttls: {"he":  "פורים טריפולי", "en":"Purim of Tripoli"}, type: "D", st: {mon: 5, d: 15}, urls: {"en":"https://www.jewishencyclopedia.com/articles/12450-purims-special#anchor26"}},
    ]
}
