{
    titles: {"*": "PR"},
    "//": "Puerto Rico",
    defaultLocale: "en",
    calendarCode: "gre",
    calendarColor: {red: 0.10, green: 0.22, blue: 0.36},
    first: {era: 1, y: 1898},
    urls: {"en": "https://en.wikipedia.org/wiki/Public_holidays_in_Puerto_Rico"},
    events: [
        {type: "D", start: {mon: 1, d: 1}, inherits: "New Year’s Day"},
        {type: "D", start: {mon: 1, d: 6}, inherits: "Epiphany"},
        {type: "D", start: {mon: 1, wkd: [2], nth: 3}, inherits: "Martin Luther King, Jr. Day"},
        {type: "D", start: {mon: 2, wkd: [2], nth: 3}, inherits: "National Heroes’ Day", urls: {"en": "https://www.officeholidays.com/holidays/puerto-rico/puerto-rico-national-heroes-day"}, first: {era: 1, y: 2014}},
        {type: "D", start: {mon: 2, wkd: [2], nth: 3}, inherits: "Presidents’ Day", urls: {"en": "https://www.officeholidays.com/holidays/puerto-rico/presidents-day"}},
        {type: "D", start: {mon: 3, d: 2}, titles: {"en": "American Citizenship Day", "es": "Día de la Ciudadanía Americana"}, first: {era: 1, y: 1917}, urls: {"en": "https://www.officeholidays.com/holidays/puerto-rico/american-citizenship-day"}},
        {type: "D", start: {mon: 3, d: 3, wkd: [2]}, titles: {"en": "American Citizenship Day (in lieu)"}, first: {era: 1, y: 1917}, urls: {"en": "https://www.officeholidays.com/holidays/puerto-rico/american-citizenship-day"}},
        {type: "D", start: {mon: 3, d: 22}, inherits: "Emancipation Day", urls: {"en": "https://nationaltoday.com/emancipation-day-puerto-rico/"}, first: {era: 1, y: 1873}},
        {type: "D", start: {Easter:  "Easter", offsetD: -2}, urls: {"en": "https://www.officeholidays.com/holidays/puerto-rico/good-friday"}, inherits: "Good Friday"},
        {type: "D", start: {Easter:  "Easter"}, inherits: "Easter Sunday"},
        {type: "D", start: {mon: 5, wkd: [1], nth: 1}, urls: {"en": "https://www.officeholidays.com/holidays/puerto-rico/mothers-day"}, inherits: "Mother’s Day"},
        {type: "D", start: {mon: 5, wkd: [2], nth: -1}, urls: {"en": "https://www.officeholidays.com/holidays/puerto-rico/memorial-day"}, inherits: "Memorial Day"},
        {type: "D", start: {mon: 6, wkd: [1], nth: 3}, urls: {"en": "https://www.officeholidays.com/holidays/puerto-rico/fathers-day"}, inherits: "Father’s Day"},
        {type: "D", start: {mon: 7, d: 4}, urls: {"en": "https://www.officeholidays.com/holidays/puerto-rico/usa-independence-day"}, inherits: "Independence Day"},
        {type: "D", start: {mon: 9, wkd: [2], nth: 1}, urls: {"en": "https://www.officeholidays.com/holidays/puerto-rico/labor-day"}, inherits: "Labour Day"},
        {type: "D", start: {mon: 10, wkd: [2], nth: 2}, urls: {"en": "https://www.officeholidays.com/holidays/puerto-rico/columbus-day"}, inherits: "Columbus Day"},
        {type: "D", start: {era: 1, y: 2024, mon: 11, d: 5}, inherits: "National Holiday", urls: {"en": "https://www.officeholidays.com/holidays/puerto-rico/puerto-rico-election-day"}},
        {type: "D", start: {mon: 11, d: 11}, urls: {"en": "https://www.officeholidays.com/holidays/puerto-rico/veterans-day"}, inherits: "Veterans Day"},
        {type: "D", start: {mon: 11, d: 19}, titles: {"en": "Discovery of Puerto Rico Day", "es": "Día del Descubrimiento de Puerto Rico"}, urls: {"en": "https://www.daysoftheyear.com/days/discovery-of-puerto-rico-day/"}, first: {era: 1, y: 1493}, inherits: "Discovery Day"},
        {type: "D", start: {mon: 11, wkd: [5], nth: 4}, urls: {"en": "https://www.officeholidays.com/holidays/puerto-rico/thanksgiving"}, inherits: "Thanksgiving Day"},
        {type: "D", start: {mon: 12, d: 24}, inherits: "Christmas Eve"},
        {type: "D", start: {mon: 12, d: 25}, inherits: "Christmas Day"},
        
        {type: "D", start: {mon: 1, wkd: [2], nth: 2}, titles: {"en": "Birthday of Eugenio María de Hostos", "es": "Natalicio de Eugenio María de Hostos"}, urls: {"en": "https://en.wikipedia.org/wiki/Eugenio_Mar%C3%ADa_de_Hostos"}, inherits: "*BDay*"},
        {type: "D", start: {mon: 2, d: 18}, titles: {"en": "Birthday of Luis Muñoz Marín", "es": "Natalicio de Luis Muñoz Marín"}, urls: {"en": "https://en.wikipedia.org/wiki/Luis_Mu%C3%B1oz_Mar%C3%ADn"}, inherits: "*BDay*"},
        {titles: {"en": "Birthday of José de Diego", "es": "Natalicio de José de Diego"}, type: "D", start: {mon: 4, d: 16}, urls: {"en": "https://en.wikipedia.org/wiki/Jos%C3%A9_de_Diego"}, inherits: "*BDay*"},
        {titles: {"en": "Birthday of Don Luis Muñoz Rivera", "es": "Natalicio de Don Luis Muñoz Rivera"}, type: "D", start: {mon: 7, wkd: [2], nth: 3}, urls: {"en": "https://nationaltoday.com/birthday-of-don-luis-munoz-rivera/"}, inherits: "*BDay*"},
        {inherits: "Constitution Day", type: "D", start: {mon: 7, d: 25}, first: {era: 1, y: 1953}, urls: {"en": "https://nationaltoday.com/puerto-rican-constitution-day/"}, titles: {"en": "Puerto Rico Constitution Day", "es": "Constitución de Puerto Rico"}},
        {titles: {"en": "Birthday of Dr. José Celso Barbosa", "es": "Natalicio de Dr. José Celso Barbosa"}, type: "D", start: {mon: 7, d: 27}, urls: {"en": "https://en.wikipedia.org/wiki/Jos%C3%A9_Celso_Barbosa"}, inherits: "*BDay*"},
        {type: "D", start: {mon: 2, wkd: [2], nth: 3}, urls: {"en": "https://nationaltoday.com/the-day-of-illustrious-puerto-ricans/"}, titles: {"en": "Day of Illustrious Puerto Ricans"}},

        {inherits: "Epiphany Eve", type: "D", start: {mon: 1, d: 5}},
        {type: "D", start: {Easter:  "Easter", offsetD: -46}, inherits: "Ash Wednesday"},
        {type: "D", start: {Easter:  "Easter", offsetD: -7}, inherits: "Palm Sunday"},
        {type: "D", start: {mon: 6, d: 24}, inherits: "St. John’s Day"},
        {type: "D", start: {mon: 12, d: 28}, inherits: "Holy Innocents Day"},
    ]
}
