{
    "titles": {"en": "Sun", "he": "שמש"},
    "supportedLocales": ["en", "he"],
    "defaultLocale": "en",
    "calendarCode": "gre*",
    "calendarColor": {"red":  1.0, "green":  1.0, "blue":  0.0},
    "eventSpecifications": [
        {"titles": {"en": "Sunrise", "he": "נץ החמה", "ar": "شروق"}, "startDateSpecification": {"type": "degreesBelowHorizon", "degreesBelowHorizon": 0.8333333333, "rising": true, "offset": 0.0}, "category": "Sunrise"},
        {"titles": {"en": "Sunset", "he": "שקיעת החמה", "ar": "غروب"}, "startDateSpecification": {"type": "degreesBelowHorizon", "degreesBelowHorizon": 0.8333333333, "rising": false, "offset": 0.0}, "category": "Sunset"},

        {
            "titles": {
                "en": "Civil dawn",
                "he": "שחר אזרחי"
            },
            "startDateSpecification": {
                "type": "degreesBelowHorizon",
                "degreesBelowHorizon":  6.0,
                "rising":  true,
                "offset":  0
            }, "category": "civilDawn"
        },
        {
            "titles": {
                "en": "Civil dusk",
                "he": "בין הערביים אזרחי"
            },
            "startDateSpecification": {
                "type": "degreesBelowHorizon",
                "degreesBelowHorizon":  6.0,
                "rising":  false,
                "offset":  0
            }, "category": "civilDusk"
        },
        
        {
            "titles": {
                "en": "Nautical dawn",
                "he": "שחר ימי"
            },
            "startDateSpecification": {
                "type": "degreesBelowHorizon",
                "degreesBelowHorizon":  12.0,
                "rising":  true,
                "offset":  0
            }, "category": "nauticalDawn"
        },
        {
            "titles": {
                "en": "Nautical dusk",
                "he": "בין העבריים ימי"
            },
            "startDateSpecification": {
                "type": "degreesBelowHorizon",
                "degreesBelowHorizon":  12.0,
                "rising":  false,
                "offset":  0
            }, "category": "nauticalDusk"
        },
        
        {
            "titles": {
                "en": "Astronomical dawn",
                "he": "שחר אסטרונומי"
            },
            "startDateSpecification": {
                "type": "degreesBelowHorizon",
                "degreesBelowHorizon":  18.0,
                "rising":  true,
                "offset":  0
            }, "category": "astronomicalDawn"
        },
        {
            "titles": {
                "en": "Astronomical dusk",
                "he": "בין הערביים אסטרונומי"
            },
            "startDateSpecification": {
                "type": "degreesBelowHorizon",
                "degreesBelowHorizon":  18.0,
                "rising":  false,
                "offset":  0
            }, "category": "astronomicalDusk"
        }
    ]
}
