{
    ttls: {"*":"TW"},
    "//":"Taiwan",
    "TODO":"Farmer’s Day, Dongzhi Festival",
    defLocale: "en",
    cal: "gre",
    color: {red: 0.00, green: 0.00, blue: 0.58},
    urls: {"en":"https://en.wikipedia.org/wiki/Public_holidays_in_Taiwan"},
    fst: {era: 1, y: 1949},
    evts: [
        {ty: "D", st: {mon: 1, d: 1}, ttls: {"en":"Founding of the Republic of China"}, urls: {"en":"https://www.officeholidays.com/holidays/taiwan/taiwan-republic-day"}, inherits: "Republic Day"},
        {ty: "D", st: {mon: 1, d: 1}, inherits: "New Year’s Day"},
        {ty: "D", st: {mon: 1, d: 2, wkd: [2]}, inherits: "Republic Day Holiday", urls: {"en":"https://www.officeholidays.com/holidays/taiwan/taiwan-republic-day"}},
        {ty: "D", st: {mon: 2, d: 27, wkd: [2, 6]}, ttls: {"en":"Peace Memorial Day Holiday"}, urls: {"en":"https://www.officeholidays.com/holidays/taiwan/peace-memorial-day"}},
        {ty: "D", st: {mon: 2, d: 28}, ttls: {"en":"Peace Memorial Day", "zh":"228和平紀念日"}, urls: {"en":"https://nationaltoday.com/228-memorial-day/"}, fst: {era: 1, y: 1995}, notes: {"en":"228 Memorial Day\n228 Peace Day\nFebruary 28 Peace Memorial Day"}},
        {ty: "D", st: {mon: 3, d: 1}, urls: {"en":"https://www.officeholidays.com/holidays/taiwan/peace-memorial-day"}, ttls: {"en":"Peace Memorial Day (in lieu)"}},
        {ty: "D", st: {mon: 4, d: 3, wkd: [2, 5, 6]}, ttls: {"en":"Children’s Day (in lieu)"}, inherits: "Children’s Day", fst: {era: 1, y: 1931}},
        {ty: "D", st: {mon: 4, d: 4}, inherits: "Children’s Day", fst: {era: 1, y: 1931}},
        {ty: "D", st: {misc: "Mar", offsetD: 15}, inherits: "Tomb-Sweeping Day", urls: {"en":"https://www.officeholidays.com/holidays/taiwan/ching-ming-festival"}},
        {ty: "D", st: {mon: 5, d: 1}, inherits: "Labour Day", urls: {"en":"https://www.officeholidays.com/holidays/taiwan/labour-day"}},
        {ty: "D", st: {mon: 5, wkd: [1], nth: 2}, inherits: "Mother’s Day"},
        {ty: "D", st: {mon: 8, d: 8}, inherits: "Father’s Day"},
        {ty: "D", st: {mon: 10, d: 10}, inherits: "N Day", notes: {"en":"Double Ten Day", "zh":"雙十節"}, urls: {"en":"https://nationaltoday.com/taiwan-national-day-double-ten-day/"}, fst: {era: 1, y: 1911}},
        
        {ty: "D", st: {mon: 3, d: 12}, inherits: "Arbor Day"},
        {inherits: "Youth Day", ty: "D", st: {mon: 3, d: 29}},
        {ty: "D", st: {mon: 5, d: 1}, inherits: "Labour Day"},
        {ty: "D", st: {mon: 5, d: 4}, urls: {"en":"https://en.wikipedia.org/wiki/Literary_Day"}, ttls: {"en":"Literary Day", "zh":"五四文藝節", "zh_CN":"五四文艺节"}},
        {ty: "D", st: {mon: 6, d: 3}, urls: {"en":"https://nationaltoday.com/opium-suppression-movement-day/"}, ttls: {"en":"Opium Suppression Movement Day", "zh":"禁菸節"}},
        {ty: "D", st: {mon: 9, d: 1}, ttls: {"en":"Journalists’ Day", "zh":"記者節"}},
        {ty: "D", st: {mon: 9, d: 3}, inherits: "Armed Forces Day"},
        {ty: "D", st: {mon: 9, d: 28}, ttls: {"en":"Confucius’s Birthday","nl":"Verjaardag van Confucius","uk":"День народження Конфуція","yue":"孔聖誕","zh":"孔子誕辰日"}, inherits: "Teacher’s Day", urls: {"en":"https://www.officeholidays.com/holidays/taiwan/taiwan-teachers-day"}},
        {ty: "D", st: {mon: 9, d: 29, wkd: [2]}, ttls: {"en":"Confucius’s Birthday (in lieu)"}, inherits: "Teacher’s Day", urls: {"en":"https://www.officeholidays.com/holidays/taiwan/taiwan-teachers-day"}},
        {ty: "D", st: {mon: 10, d: 21}, ttls: {"en":"Overseas Chinese Day", "zh":"華僑節"}},
        {ty: "D", st: {mon: 10, d: 25}, ttls: {"de":"Taiwan-Rückgabe-Tag","en":"Retrocession Day","es":"Adhesión de Taiwán a la República de China","fr":"Jour de la Rétrocession","id":"Hari Penyerahan Kembali","ja":"台湾光復節","ko":"대만광복절","ms":"Hari Penyerahan Kembali","si":"යටත්ව සිටීමෙන් මිදීමේ දිනය","uk":"День ретроцесії Тайваню","vi":"Ngày Tái Độc lập","yue":"臺灣光復節","zh":"臺灣光復節"}, notes: {"en":"Taiwan Retrocession Day"}, urls: {"en":"https://www.officeholidays.com/holidays/taiwan/retrocession-day-battle-of-guningtou"}},
        {ty: "D", st: {mon: 10, d: 24, wkd: [6]}, inherits: "Retrocession Day (in lieu)"},
        {ty: "D", st: {mon: 10, d: 26, wkd: [2]}, inherits: "Retrocession Day (in lieu)"},
        {ty: "D", st: {mon: 11, d: 12}, ttls: {"en":"Sun Yat-sen’s Birthday", "zh":"國父誕辰紀念日"}, inherits: "*BDay*"},
        {ty: "D", st: {mon: 12, d: 25}, inherits: "Constitution Day"},

        {ty: "D", st: {mon: 6, d: 6}, inherits: "Engineer’s Day"},
        {ty: "D", st: {mon: 3, d: 8}, inherits: "IWD"},
        {ty: "D", st: {mon: 8, d: 14}, inherits: "Air Force Day"},
        {ty: "D", st: {mon: 9, d: 2}, inherits: "Navy Day"},
        {ty: "D", st: {mon: 9, d: 29}, inherits: "N Coffee Day"},
        {ty: "D", st: {mon: 8, wkd: [1], nth: 4}, inherits: "Grandparents’ Day", fst: {era: 1, y: 2010}},
        {ty: "D", st: {mon: 1, d: 27}, inherits: "Holocaust Memorial Day", fst: {era: 1, y: 2006}},
  ],
    tpls: {
        "Retrocession Day (in lieu)": {ty: "D", st: {mon: 10, d: 24}, ttls: {"en":"Retrocession Day (in lieu)"}, notes: {"en":"Taiwan Retrocession Day (in lieu)"}, urls: {"en":"https://www.officeholidays.com/holidays/taiwan/retrocession-day-battle-of-guningtou"}},
    }
}
